{
  "mpId": 5140,
  "ns": "52",
  "partyShort": "ПБ",
  "loyalty": {
    "votesCast": 318,
    "withParty": 313,
    "loyaltyPct": 0.9842767295597484,
    "windowFrom": "2026-04-30",
    "windowTo": "2026-06-11",
    "totalVoteItems": 414
  },
  "attendance": {
    "totalItems": 414,
    "presentCount": 318,
    "absentCount": 96,
    "presentPct": 0.7681159420289855
  },
  "cohort": {
    "size": 266,
    "votesCastMedian": 298,
    "loyaltyPctMedian": 0.975256050031723,
    "presentPctMedian": 0.718695652173913
  },
  "dissents": {
    "totalCast": 318,
    "dissentCount": 5,
    "recent": [
      {
        "date": "2026-06-04",
        "item": 66,
        "slug": "66-reshenie-za-izbirane-na-komisiya-po-politikite-za-balgarite-",
        "title": "Решение за избиране на Комисия по политиките за българите извън страната - състав и ръководство",
        "topic": "personnel",
        "mpVote": "abstain",
        "majorityVote": "yes",
        "groupSize": 99
      },
      {
        "date": "2026-05-29",
        "item": 10,
        "slug": "10-zakon-za-protivodeystvie-na-koruptsiyata-sred-litsa-zaemasht",
        "title": "Закон за противодействие на корупцията сред лица, заемащи публични длъжности - второ гласуване - член 7 - предложение от Елена Нонева и Асен Бабачев",
        "topic": "other",
        "mpVote": "abstain",
        "majorityVote": "no",
        "groupSize": 111
      },
      {
        "date": "2026-05-28",
        "item": 82,
        "slug": "82-pravilnik-za-organizatsiyata-i-deynostta-na-narodnoto-sabran",
        "title": "Правилник за организацията и дейността на Народното събрание - член 82",
        "topic": "other",
        "mpVote": "no",
        "majorityVote": "yes",
        "groupSize": 120
      },
      {
        "date": "2026-05-28",
        "item": 35,
        "slug": "35-pravilnik-za-organizatsiyata-i-deynostta-na-narodnoto-sabran",
        "title": "Правилник за организацията и дейността на Народното събрание - член 41 - предложение от Петър Петров",
        "topic": "other",
        "mpVote": "abstain",
        "majorityVote": "no",
        "groupSize": 112
      },
      {
        "date": "2026-05-28",
        "item": 26,
        "slug": "26-pravilnik-za-organizatsiyata-i-deynostta-na-narodnoto-sabran",
        "title": "Правилник за организацията и дейността на Народното събрание - член 36 - предложение от Стою Стоев и Б. Божанов за редакция на ал.2",
        "topic": "other",
        "mpVote": "abstain",
        "majorityVote": "no",
        "groupSize": 115
      }
    ]
  },
  "similarity": {
    "topK": [
      {
        "mpId": 5076,
        "score": 0.9060187499143035,
        "overlap": 309
      },
      {
        "mpId": 5065,
        "score": 0.9044453200815528,
        "overlap": 314
      },
      {
        "mpId": 5071,
        "score": 0.8959815740297357,
        "overlap": 318
      },
      {
        "mpId": 5130,
        "score": 0.8892484675091982,
        "overlap": 307
      },
      {
        "mpId": 5135,
        "score": 0.8879844320905426,
        "overlap": 311
      },
      {
        "mpId": 5253,
        "score": 0.8847846238500912,
        "overlap": 313
      },
      {
        "mpId": 5296,
        "score": 0.8831157194574106,
        "overlap": 312
      },
      {
        "mpId": 5225,
        "score": 0.8816434473237573,
        "overlap": 313
      },
      {
        "mpId": 5279,
        "score": 0.8810485477959067,
        "overlap": 309
      },
      {
        "mpId": 5199,
        "score": 0.8800493454315168,
        "overlap": 303
      },
      {
        "mpId": 5239,
        "score": 0.878219652794677,
        "overlap": 314
      },
      {
        "mpId": 5263,
        "score": 0.8781218080602365,
        "overlap": 316
      },
      {
        "mpId": 5213,
        "score": 0.8780619425491409,
        "overlap": 315
      },
      {
        "mpId": 5278,
        "score": 0.8774500372920108,
        "overlap": 314
      },
      {
        "mpId": 5271,
        "score": 0.8768777721619974,
        "overlap": 312
      },
      {
        "mpId": 5094,
        "score": 0.8746302562283664,
        "overlap": 316
      },
      {
        "mpId": 5178,
        "score": 0.8739906353296442,
        "overlap": 312
      },
      {
        "mpId": 5179,
        "score": 0.8739906353296442,
        "overlap": 314
      },
      {
        "mpId": 5210,
        "score": 0.8738384132504139,
        "overlap": 316
      },
      {
        "mpId": 5069,
        "score": 0.8709430234686824,
        "overlap": 298
      }
    ],
    "bottomK": [
      {
        "mpId": 5194,
        "score": -0.12716767341473292,
        "overlap": 170
      },
      {
        "mpId": 5074,
        "score": -0.12202549494473623,
        "overlap": 224
      },
      {
        "mpId": 5171,
        "score": -0.10937868334203406,
        "overlap": 241
      },
      {
        "mpId": 5334,
        "score": -0.025691749776935394,
        "overlap": 14
      },
      {
        "mpId": 5247,
        "score": 0,
        "overlap": 203
      },
      {
        "mpId": 5060,
        "score": 0.0036046394170269848,
        "overlap": 227
      },
      {
        "mpId": 5273,
        "score": 0.023295315340988904,
        "overlap": 275
      },
      {
        "mpId": 5101,
        "score": 0.023334500087507287,
        "overlap": 278
      },
      {
        "mpId": 5258,
        "score": 0.02980856241922593,
        "overlap": 201
      },
      {
        "mpId": 5234,
        "score": 0.06431852004310569,
        "overlap": 254
      },
      {
        "mpId": 5185,
        "score": 0.0706003013438613,
        "overlap": 277
      },
      {
        "mpId": 4099,
        "score": 0.07707524933080619,
        "overlap": 5
      },
      {
        "mpId": 4105,
        "score": 0.07707524933080619,
        "overlap": 5
      },
      {
        "mpId": 4110,
        "score": 0.07707524933080619,
        "overlap": 5
      },
      {
        "mpId": 5159,
        "score": 0.0780819626123435,
        "overlap": 256
      },
      {
        "mpId": 5100,
        "score": 0.11561287399620927,
        "overlap": 20
      },
      {
        "mpId": 5148,
        "score": 0.11626057023490369,
        "overlap": 142
      },
      {
        "mpId": 4100,
        "score": 0.12845874888467698,
        "overlap": 5
      },
      {
        "mpId": 4109,
        "score": 0.12845874888467698,
        "overlap": 5
      },
      {
        "mpId": 4111,
        "score": 0.12845874888467698,
        "overlap": 5
      }
    ]
  }
}
