[{"partyNum":5,"totalVotes":1,"pref":"105","oblast":"SFO","ekatte":"58030","obshtina":"SFO34","allVotes":1897,"partyVotes":4,"partyPrefs":2},{"partyNum":6,"totalVotes":8,"pref":"101","oblast":"SFO","ekatte":"58030","obshtina":"SFO34","allVotes":1897,"partyVotes":94,"partyPrefs":28},{"partyNum":6,"totalVotes":1,"pref":"105","oblast":"SFO","ekatte":"58030","obshtina":"SFO34","allVotes":1897,"partyVotes":94,"partyPrefs":28},{"partyNum":6,"totalVotes":10,"pref":"106","oblast":"SFO","ekatte":"58030","obshtina":"SFO34","allVotes":1897,"partyVotes":94,"partyPrefs":28},{"partyNum":8,"totalVotes":28,"pref":"101","oblast":"SFO","ekatte":"58030","obshtina":"SFO34","allVotes":1897,"partyVotes":107,"partyPrefs":62},{"partyNum":8,"totalVotes":3,"pref":"106","oblast":"SFO","ekatte":"58030","obshtina":"SFO34","allVotes":1897,"partyVotes":107,"partyPrefs":62},{"partyNum":8,"totalVotes":17,"pref":"109","oblast":"SFO","ekatte":"58030","obshtina":"SFO34","allVotes":1897,"partyVotes":107,"partyPrefs":62},{"partyNum":8,"totalVotes":6,"pref":"111","oblast":"SFO","ekatte":"58030","obshtina":"SFO34","allVotes":1897,"partyVotes":107,"partyPrefs":62},{"partyNum":8,"totalVotes":1,"pref":"115","oblast":"SFO","ekatte":"58030","obshtina":"SFO34","allVotes":1897,"partyVotes":107,"partyPrefs":62},{"partyNum":9,"totalVotes":2,"pref":"105","oblast":"SFO","ekatte":"58030","obshtina":"SFO34","allVotes":1897,"partyVotes":24,"partyPrefs":5},{"partyNum":10,"totalVotes":14,"pref":"101","oblast":"SFO","ekatte":"58030","obshtina":"SFO34","allVotes":1897,"partyVotes":728,"partyPrefs":245},{"partyNum":10,"totalVotes":94,"pref":"102","oblast":"SFO","ekatte":"58030","obshtina":"SFO34","allVotes":1897,"partyVotes":728,"partyPrefs":245},{"partyNum":10,"totalVotes":7,"pref":"104","oblast":"SFO","ekatte":"58030","obshtina":"SFO34","allVotes":1897,"partyVotes":728,"partyPrefs":245},{"partyNum":10,"totalVotes":32,"pref":"105","oblast":"SFO","ekatte":"58030","obshtina":"SFO34","allVotes":1897,"partyVotes":728,"partyPrefs":245,"lyTotalVotes":19},{"partyNum":10,"totalVotes":20,"pref":"106","oblast":"SFO","ekatte":"58030","obshtina":"SFO34","allVotes":1897,"partyVotes":728,"partyPrefs":245,"lyTotalVotes":3},{"partyNum":10,"totalVotes":5,"pref":"108","oblast":"SFO","ekatte":"58030","obshtina":"SFO34","allVotes":1897,"partyVotes":728,"partyPrefs":245},{"partyNum":10,"totalVotes":52,"pref":"110","oblast":"SFO","ekatte":"58030","obshtina":"SFO34","allVotes":1897,"partyVotes":728,"partyPrefs":245},{"partyNum":10,"totalVotes":6,"pref":"116","oblast":"SFO","ekatte":"58030","obshtina":"SFO34","allVotes":1897,"partyVotes":728,"partyPrefs":245},{"partyNum":11,"totalVotes":27,"pref":"101","oblast":"SFO","ekatte":"58030","obshtina":"SFO34","allVotes":1897,"partyVotes":586,"partyPrefs":213},{"partyNum":11,"totalVotes":10,"pref":"102","oblast":"SFO","ekatte":"58030","obshtina":"SFO34","allVotes":1897,"partyVotes":586,"partyPrefs":213,"lyTotalVotes":9},{"partyNum":11,"totalVotes":72,"pref":"103","oblast":"SFO","ekatte":"58030","obshtina":"SFO34","allVotes":1897,"partyVotes":586,"partyPrefs":213},{"partyNum":11,"totalVotes":1,"pref":"105","oblast":"SFO","ekatte":"58030","obshtina":"SFO34","allVotes":1897,"partyVotes":586,"partyPrefs":213},{"partyNum":11,"totalVotes":10,"pref":"108","oblast":"SFO","ekatte":"58030","obshtina":"SFO34","allVotes":1897,"partyVotes":586,"partyPrefs":213},{"partyNum":11,"totalVotes":8,"pref":"110","oblast":"SFO","ekatte":"58030","obshtina":"SFO34","allVotes":1897,"partyVotes":586,"partyPrefs":213},{"partyNum":11,"totalVotes":38,"pref":"111","oblast":"SFO","ekatte":"58030","obshtina":"SFO34","allVotes":1897,"partyVotes":586,"partyPrefs":213},{"partyNum":11,"totalVotes":29,"pref":"112","oblast":"SFO","ekatte":"58030","obshtina":"SFO34","allVotes":1897,"partyVotes":586,"partyPrefs":213},{"partyNum":11,"totalVotes":3,"pref":"115","oblast":"SFO","ekatte":"58030","obshtina":"SFO34","allVotes":1897,"partyVotes":586,"partyPrefs":213},{"partyNum":14,"totalVotes":2,"pref":"102","oblast":"SFO","ekatte":"58030","obshtina":"SFO34","allVotes":1897,"partyVotes":25,"partyPrefs":3},{"partyNum":16,"totalVotes":27,"pref":"102","oblast":"SFO","ekatte":"58030","obshtina":"SFO34","allVotes":1897,"partyVotes":70,"partyPrefs":29},{"partyNum":17,"totalVotes":10,"pref":"101","oblast":"SFO","ekatte":"58030","obshtina":"SFO34","allVotes":1897,"partyVotes":190,"partyPrefs":99},{"partyNum":17,"totalVotes":72,"pref":"102","oblast":"SFO","ekatte":"58030","obshtina":"SFO34","allVotes":1897,"partyVotes":190,"partyPrefs":99,"lyTotalVotes":72},{"partyNum":21,"totalVotes":2,"pref":"101","oblast":"SFO","ekatte":"58030","obshtina":"SFO34","allVotes":1897,"partyVotes":35,"partyPrefs":11,"lyTotalVotes":6},{"partyNum":21,"totalVotes":5,"pref":"102","oblast":"SFO","ekatte":"58030","obshtina":"SFO34","allVotes":1897,"partyVotes":35,"partyPrefs":11},{"partyNum":21,"totalVotes":1,"pref":"107","oblast":"SFO","ekatte":"58030","obshtina":"SFO34","allVotes":1897,"partyVotes":35,"partyPrefs":11},{"partyNum":4,"totalVotes":0,"pref":"109","oblast":"SFO","ekatte":"58030","obshtina":"SFO34","allVotes":1897,"partyVotes":9,"partyPrefs":1,"lyTotalVotes":7},{"partyNum":11,"totalVotes":1,"pref":"114","oblast":"SFO","ekatte":"58030","obshtina":"SFO34","allVotes":1897,"partyVotes":586,"partyPrefs":213,"lyTotalVotes":5},{"partyNum":11,"totalVotes":3,"pref":"107","oblast":"SFO","ekatte":"58030","obshtina":"SFO34","allVotes":1897,"partyVotes":586,"partyPrefs":213,"lyTotalVotes":30},{"partyNum":8,"totalVotes":3,"pref":"108","oblast":"SFO","ekatte":"58030","obshtina":"SFO34","allVotes":1897,"partyVotes":107,"partyPrefs":62,"lyTotalVotes":1},{"partyNum":10,"totalVotes":5,"pref":"103","oblast":"SFO","ekatte":"58030","obshtina":"SFO34","allVotes":1897,"partyVotes":728,"partyPrefs":245,"lyTotalVotes":9},{"partyNum":3,"totalVotes":1,"pref":"103","oblast":"SFO","ekatte":"58030","obshtina":"SFO34","allVotes":1897,"partyVotes":6,"partyPrefs":1},{"partyNum":6,"totalVotes":6,"pref":"108","oblast":"SFO","ekatte":"58030","obshtina":"SFO34","allVotes":1897,"partyVotes":94,"partyPrefs":28},{"partyNum":8,"totalVotes":1,"pref":"103","oblast":"SFO","ekatte":"58030","obshtina":"SFO34","allVotes":1897,"partyVotes":107,"partyPrefs":62},{"partyNum":8,"totalVotes":1,"pref":"104","oblast":"SFO","ekatte":"58030","obshtina":"SFO34","allVotes":1897,"partyVotes":107,"partyPrefs":62,"lyTotalVotes":5},{"partyNum":10,"totalVotes":4,"pref":"111","oblast":"SFO","ekatte":"58030","obshtina":"SFO34","allVotes":1897,"partyVotes":728,"partyPrefs":245,"lyTotalVotes":1},{"partyNum":11,"totalVotes":3,"pref":"104","oblast":"SFO","ekatte":"58030","obshtina":"SFO34","allVotes":1897,"partyVotes":586,"partyPrefs":213,"lyTotalVotes":3},{"partyNum":11,"totalVotes":3,"pref":"106","oblast":"SFO","ekatte":"58030","obshtina":"SFO34","allVotes":1897,"partyVotes":586,"partyPrefs":213,"lyTotalVotes":5},{"partyNum":12,"totalVotes":1,"pref":"104","oblast":"SFO","ekatte":"58030","obshtina":"SFO34","allVotes":1897,"partyVotes":5,"partyPrefs":3},{"partyNum":16,"totalVotes":2,"pref":"103","oblast":"SFO","ekatte":"58030","obshtina":"SFO34","allVotes":1897,"partyVotes":70,"partyPrefs":29},{"partyNum":17,"totalVotes":15,"pref":"103","oblast":"SFO","ekatte":"58030","obshtina":"SFO34","allVotes":1897,"partyVotes":190,"partyPrefs":99},{"partyNum":21,"totalVotes":3,"pref":"105","oblast":"SFO","ekatte":"58030","obshtina":"SFO34","allVotes":1897,"partyVotes":35,"partyPrefs":11},{"partyNum":17,"totalVotes":1,"pref":"107","oblast":"SFO","ekatte":"58030","obshtina":"SFO34","allVotes":1897,"partyVotes":190,"partyPrefs":99,"lyTotalVotes":6},{"partyNum":9,"totalVotes":0,"pref":"103","oblast":"SFO","ekatte":"58030","obshtina":"SFO34","allVotes":1897,"partyVotes":24,"partyPrefs":5,"lyTotalVotes":2},{"partyNum":10,"totalVotes":2,"pref":"113","oblast":"SFO","ekatte":"58030","obshtina":"SFO34","allVotes":1897,"partyVotes":728,"partyPrefs":245,"lyTotalVotes":1},{"partyNum":17,"totalVotes":0,"pref":"105","oblast":"SFO","ekatte":"58030","obshtina":"SFO34","allVotes":1897,"partyVotes":190,"partyPrefs":99,"lyTotalVotes":2},{"partyNum":17,"totalVotes":0,"pref":"106","oblast":"SFO","ekatte":"58030","obshtina":"SFO34","allVotes":1897,"partyVotes":190,"partyPrefs":99,"lyTotalVotes":2},{"partyNum":4,"totalVotes":1,"pref":"104","oblast":"SFO","ekatte":"58030","obshtina":"SFO34","allVotes":1897,"partyVotes":9,"partyPrefs":1},{"partyNum":5,"totalVotes":1,"pref":"102","oblast":"SFO","ekatte":"58030","obshtina":"SFO34","allVotes":1897,"partyVotes":4,"partyPrefs":2},{"partyNum":9,"totalVotes":1,"pref":"101","oblast":"SFO","ekatte":"58030","obshtina":"SFO34","allVotes":1897,"partyVotes":24,"partyPrefs":5},{"partyNum":10,"totalVotes":3,"pref":"107","oblast":"SFO","ekatte":"58030","obshtina":"SFO34","allVotes":1897,"partyVotes":728,"partyPrefs":245},{"partyNum":11,"totalVotes":2,"pref":"113","oblast":"SFO","ekatte":"58030","obshtina":"SFO34","allVotes":1897,"partyVotes":586,"partyPrefs":213},{"partyNum":17,"totalVotes":1,"pref":"108","oblast":"SFO","ekatte":"58030","obshtina":"SFO34","allVotes":1897,"partyVotes":190,"partyPrefs":99},{"partyNum":10,"totalVotes":0,"pref":"109","oblast":"SFO","ekatte":"58030","obshtina":"SFO34","allVotes":1897,"partyVotes":728,"partyPrefs":245,"lyTotalVotes":4},{"partyNum":16,"totalVotes":0,"pref":"108","oblast":"SFO","ekatte":"58030","obshtina":"SFO34","allVotes":1897,"partyVotes":70,"partyPrefs":29,"lyTotalVotes":1},{"partyNum":6,"totalVotes":1,"pref":"102","oblast":"SFO","ekatte":"58030","obshtina":"SFO34","allVotes":1897,"partyVotes":94,"partyPrefs":28},{"partyNum":6,"totalVotes":2,"pref":"107","oblast":"SFO","ekatte":"58030","obshtina":"SFO34","allVotes":1897,"partyVotes":94,"partyPrefs":28},{"partyNum":8,"totalVotes":1,"pref":"107","oblast":"SFO","ekatte":"58030","obshtina":"SFO34","allVotes":1897,"partyVotes":107,"partyPrefs":62},{"partyNum":9,"totalVotes":1,"pref":"110","oblast":"SFO","ekatte":"58030","obshtina":"SFO34","allVotes":1897,"partyVotes":24,"partyPrefs":5},{"partyNum":2,"totalVotes":1,"pref":"101","oblast":"SFO","ekatte":"58030","obshtina":"SFO34","allVotes":1897,"partyVotes":3,"partyPrefs":2},{"partyNum":2,"totalVotes":1,"pref":"102","oblast":"SFO","ekatte":"58030","obshtina":"SFO34","allVotes":1897,"partyVotes":3,"partyPrefs":2},{"partyNum":8,"totalVotes":1,"pref":"110","oblast":"SFO","ekatte":"58030","obshtina":"SFO34","allVotes":1897,"partyVotes":107,"partyPrefs":62},{"partyNum":9,"totalVotes":1,"pref":"111","oblast":"SFO","ekatte":"58030","obshtina":"SFO34","allVotes":1897,"partyVotes":24,"partyPrefs":5},{"partyNum":10,"totalVotes":1,"pref":"115","oblast":"SFO","ekatte":"58030","obshtina":"SFO34","allVotes":1897,"partyVotes":728,"partyPrefs":245},{"partyNum":11,"totalVotes":1,"pref":"109","oblast":"SFO","ekatte":"58030","obshtina":"SFO34","allVotes":1897,"partyVotes":586,"partyPrefs":213},{"partyNum":11,"totalVotes":2,"pref":"116","oblast":"SFO","ekatte":"58030","obshtina":"SFO34","allVotes":1897,"partyVotes":586,"partyPrefs":213},{"partyNum":12,"totalVotes":1,"pref":"102","oblast":"SFO","ekatte":"58030","obshtina":"SFO34","allVotes":1897,"partyVotes":5,"partyPrefs":3},{"partyNum":12,"totalVotes":1,"pref":"103","oblast":"SFO","ekatte":"58030","obshtina":"SFO34","allVotes":1897,"partyVotes":5,"partyPrefs":3},{"partyNum":14,"totalVotes":1,"pref":"101","oblast":"SFO","ekatte":"58030","obshtina":"SFO34","allVotes":1897,"partyVotes":25,"partyPrefs":3},{"partyNum":4,"totalVotes":0,"pref":"110","oblast":"SFO","ekatte":"58030","obshtina":"SFO34","allVotes":1897,"partyVotes":9,"partyPrefs":1,"lyTotalVotes":1}]