[{"partyNum":10,"totalVotes":3,"allVotes":38,"partyVotes":16,"pref":"101","oblast":"GAB","ekatte":"73434","obshtina":"GAB29"},{"partyNum":11,"totalVotes":0,"allVotes":38,"partyVotes":16,"pref":"105","oblast":"GAB","ekatte":"73434","obshtina":"GAB29"},{"partyNum":11,"totalVotes":0,"allVotes":38,"partyVotes":16,"pref":"103","oblast":"GAB","ekatte":"73434","obshtina":"GAB29"},{"partyNum":10,"totalVotes":0,"allVotes":38,"partyVotes":16,"pref":"107","oblast":"GAB","ekatte":"73434","obshtina":"GAB29"}]