{
  "obshtina": "BLG52",
  "generatedAt": "2026-06-28T17:25:30.376Z",
  "changes": [
    {
      "contractNumber": "BG-RRP-4.020-0127",
      "title": "Енергийно обновяване сградата на читалище „Просвета“, находяща се в УПИ II, кв.36, с. Абланица, община Хаджидимово, област Благоевград",
      "type": "modified",
      "changedFields": [
        "paidEur"
      ],
      "prevTotalEur": 462296.89,
      "totalEur": 462296.89,
      "paidEur": 406005.73,
      "status": "В изпълнение (от дата на стартиране)",
      "programCode": "2021BG-RRP",
      "programName": "Национален план за възстановяване и устойчивост",
      "beneficiaryName": "Община Хаджидимово",
      "detectedAt": "2026-06-28"
    },
    {
      "contractNumber": "BG-RRP-4.021-0174",
      "title": "Подкрепа за енергийно обновяване на сграда на Стил-76 ЕООД в сферата на търговията",
      "type": "modified",
      "changedFields": [
        "paidEur"
      ],
      "prevTotalEur": 276521.22,
      "totalEur": 276521.22,
      "paidEur": 150481.76,
      "status": "В изпълнение (от дата на стартиране)",
      "programCode": "2021BG-RRP",
      "programName": "Национален план за възстановяване и устойчивост",
      "beneficiaryName": "СТИЛ-76 ЕООД",
      "detectedAt": "2026-06-28"
    }
  ]
}
