{"section":"091400071","region":"9","region_name":"09. КЪРДЖАЛИ","zip_code":"37767","settlement":"с.Козлево","is_mobile":0,"is_ship":0,"num_machines":0,"results":{"protocol":{"ballotsReceived":200,"numRegisteredVoters":232,"totalActualVoters":37,"numAdditionalVoters":0,"numUnusedPaperBallots":0,"numInvalidAndDestroyedPaperBallots":1,"numInvalidBallotsFound":0,"numPaperBallotsFound":37,"numValidVotes":37,"numValidNoOnePaperVotes":0},"votes":[{"partyNum":4,"totalVotes":2,"paperVotes":2,"machineVotes":null},{"partyNum":9,"totalVotes":30,"paperVotes":30,"machineVotes":null},{"partyNum":28,"totalVotes":4,"paperVotes":4,"machineVotes":null},{"partyNum":29,"totalVotes":1,"paperVotes":1,"machineVotes":null}]},"oblast":"KRZ","obshtina":"KRZ14","ekatte":"37767"}