[{"key":"BG413","ekatte":"02600","name":"Баничан","oblast":"BLG","obshtina":"BLG11","kmetstvo":"BLG11-01","t_v_m":"с.","sections":[],"results":{"votes":[{"partyNum":3,"totalVotes":4,"machineVotes":0,"paperVotes":4},{"partyNum":4,"totalVotes":6,"machineVotes":0,"paperVotes":6},{"partyNum":5,"totalVotes":1,"machineVotes":0,"paperVotes":1},{"partyNum":6,"totalVotes":9,"machineVotes":0,"paperVotes":9},{"partyNum":9,"totalVotes":1,"machineVotes":0,"paperVotes":1},{"partyNum":10,"totalVotes":131,"machineVotes":0,"paperVotes":131},{"partyNum":11,"totalVotes":78,"machineVotes":0,"paperVotes":78},{"partyNum":17,"totalVotes":27,"machineVotes":0,"paperVotes":27},{"partyNum":21,"totalVotes":35,"machineVotes":0,"paperVotes":35}],"protocol":{"ballotsReceived":500,"numAdditionalVoters":2,"numInvalidAndDestroyedPaperBallots":1,"numInvalidBallotsFound":26,"numPaperBallotsFound":323,"numRegisteredVoters":502,"numUnusedPaperBallots":173,"numValidNoOnePaperVotes":5,"numValidVotes":323,"totalActualVoters":354}}},{"key":"BG413","ekatte":"05606","name":"Борово","oblast":"BLG","obshtina":"BLG11","kmetstvo":"BLG11-02","t_v_m":"с.","sections":[],"results":{"votes":[{"partyNum":3,"totalVotes":2,"machineVotes":0,"paperVotes":2},{"partyNum":4,"totalVotes":4,"machineVotes":0,"paperVotes":4},{"partyNum":6,"totalVotes":15,"machineVotes":0,"paperVotes":15},{"partyNum":8,"totalVotes":7,"machineVotes":0,"paperVotes":7},{"partyNum":9,"totalVotes":1,"machineVotes":0,"paperVotes":1},{"partyNum":10,"totalVotes":228,"machineVotes":0,"paperVotes":228},{"partyNum":11,"totalVotes":164,"machineVotes":0,"paperVotes":164},{"partyNum":12,"totalVotes":1,"machineVotes":0,"paperVotes":1},{"partyNum":13,"totalVotes":1,"machineVotes":0,"paperVotes":1},{"partyNum":14,"totalVotes":5,"machineVotes":0,"paperVotes":5},{"partyNum":17,"totalVotes":60,"machineVotes":0,"paperVotes":60},{"partyNum":21,"totalVotes":9,"machineVotes":0,"paperVotes":9},{"partyNum":1,"totalVotes":1,"machineVotes":0,"paperVotes":1},{"partyNum":7,"totalVotes":1,"machineVotes":0,"paperVotes":1},{"partyNum":16,"totalVotes":3,"machineVotes":0,"paperVotes":3},{"partyNum":20,"totalVotes":1,"machineVotes":0,"paperVotes":1}],"protocol":{"ballotsReceived":1000,"numInvalidBallotsFound":29,"numPaperBallotsFound":541,"numRegisteredVoters":961,"numUnusedPaperBallots":456,"numValidNoOnePaperVotes":9,"numValidVotes":541,"totalActualVoters":579,"numAdditionalVoters":4,"numInvalidAndDestroyedPaperBallots":1}}},{"key":"BG413","ekatte":"06306","name":"Брезница","oblast":"BLG","obshtina":"BLG11","kmetstvo":"BLG11-03","t_v_m":"с.","sections":[],"results":{"votes":[{"partyNum":9,"totalVotes":1229,"machineVotes":0,"paperVotes":1229},{"partyNum":10,"totalVotes":24,"machineVotes":0,"paperVotes":24},{"partyNum":11,"totalVotes":40,"machineVotes":0,"paperVotes":40},{"partyNum":13,"totalVotes":518,"machineVotes":0,"paperVotes":518},{"partyNum":17,"totalVotes":18,"machineVotes":0,"paperVotes":18},{"partyNum":21,"totalVotes":1,"machineVotes":0,"paperVotes":1},{"partyNum":4,"totalVotes":4,"machineVotes":0,"paperVotes":4},{"partyNum":6,"totalVotes":8,"machineVotes":0,"paperVotes":8},{"partyNum":7,"totalVotes":1,"machineVotes":0,"paperVotes":1},{"partyNum":8,"totalVotes":3,"machineVotes":0,"paperVotes":3},{"partyNum":19,"totalVotes":2,"machineVotes":0,"paperVotes":2},{"partyNum":2,"totalVotes":1,"machineVotes":0,"paperVotes":1},{"partyNum":16,"totalVotes":3,"machineVotes":0,"paperVotes":3}],"protocol":{"ballotsReceived":3100,"numAdditionalVoters":22,"numInvalidAndDestroyedPaperBallots":5,"numInvalidBallotsFound":150,"numPaperBallotsFound":2018,"numRegisteredVoters":2994,"numUnusedPaperBallots":1077,"numValidVotes":2018,"totalActualVoters":2184,"numValidNoOnePaperVotes":16}}},{"key":"BG413","ekatte":"07003","name":"Буково","oblast":"BLG","obshtina":"BLG11","kmetstvo":"BLG11-04","t_v_m":"с.","sections":[],"results":{"votes":[{"partyNum":3,"totalVotes":1,"machineVotes":0,"paperVotes":1},{"partyNum":5,"totalVotes":1,"machineVotes":0,"paperVotes":1},{"partyNum":6,"totalVotes":1,"machineVotes":0,"paperVotes":1},{"partyNum":7,"totalVotes":1,"machineVotes":0,"paperVotes":1},{"partyNum":8,"totalVotes":3,"machineVotes":0,"paperVotes":3},{"partyNum":9,"totalVotes":433,"machineVotes":0,"paperVotes":433},{"partyNum":10,"totalVotes":11,"machineVotes":0,"paperVotes":11},{"partyNum":11,"totalVotes":8,"machineVotes":0,"paperVotes":8},{"partyNum":13,"totalVotes":73,"machineVotes":0,"paperVotes":73},{"partyNum":14,"totalVotes":1,"machineVotes":0,"paperVotes":1},{"partyNum":17,"totalVotes":2,"machineVotes":0,"paperVotes":2}],"protocol":{"ballotsReceived":900,"numAdditionalVoters":8,"numInvalidAndDestroyedPaperBallots":1,"numInvalidBallotsFound":26,"numPaperBallotsFound":564,"numRegisteredVoters":838,"numUnusedPaperBallots":333,"numValidNoOnePaperVotes":3,"numValidVotes":564,"totalActualVoters":593}}},{"key":"BG413","ekatte":"17347","name":"Господинци","oblast":"BLG","obshtina":"BLG11","kmetstvo":"BLG11-05","t_v_m":"с.","sections":[],"results":{"votes":[{"partyNum":4,"totalVotes":1,"machineVotes":0,"paperVotes":1},{"partyNum":6,"totalVotes":1,"machineVotes":0,"paperVotes":1},{"partyNum":8,"totalVotes":1,"machineVotes":0,"paperVotes":1},{"partyNum":9,"totalVotes":120,"machineVotes":0,"paperVotes":120},{"partyNum":10,"totalVotes":25,"machineVotes":0,"paperVotes":25},{"partyNum":11,"totalVotes":33,"machineVotes":0,"paperVotes":33},{"partyNum":12,"totalVotes":1,"machineVotes":0,"paperVotes":1},{"partyNum":13,"totalVotes":10,"machineVotes":0,"paperVotes":10},{"partyNum":17,"totalVotes":1,"machineVotes":0,"paperVotes":1},{"partyNum":19,"totalVotes":1,"machineVotes":0,"paperVotes":1},{"partyNum":21,"totalVotes":1,"machineVotes":0,"paperVotes":1}],"protocol":{"ballotsReceived":400,"numAdditionalVoters":5,"numInvalidAndDestroyedPaperBallots":1,"numInvalidBallotsFound":36,"numPaperBallotsFound":232,"numRegisteredVoters":385,"numUnusedPaperBallots":168,"numValidNoOnePaperVotes":1,"numValidVotes":232,"totalActualVoters":269}}},{"key":"BG413","ekatte":"17395","name":"Гоце Делчев","oblast":"BLG","obshtina":"BLG11","kmetstvo":"BLG11-00","t_v_m":"гр.","sections":[],"results":{"votes":[{"partyNum":2,"totalVotes":20,"machineVotes":0,"paperVotes":20},{"partyNum":3,"totalVotes":55,"machineVotes":0,"paperVotes":55},{"partyNum":4,"totalVotes":311,"machineVotes":0,"paperVotes":311},{"partyNum":5,"totalVotes":7,"machineVotes":0,"paperVotes":7},{"partyNum":6,"totalVotes":300,"machineVotes":0,"paperVotes":300},{"partyNum":7,"totalVotes":14,"machineVotes":0,"paperVotes":14},{"partyNum":8,"totalVotes":171,"machineVotes":0,"paperVotes":171},{"partyNum":9,"totalVotes":175,"machineVotes":0,"paperVotes":175},{"partyNum":10,"totalVotes":3648,"machineVotes":0,"paperVotes":3648},{"partyNum":11,"totalVotes":3670,"machineVotes":0,"paperVotes":3670},{"partyNum":13,"totalVotes":79,"machineVotes":0,"paperVotes":79},{"partyNum":14,"totalVotes":128,"machineVotes":0,"paperVotes":128},{"partyNum":16,"totalVotes":130,"machineVotes":0,"paperVotes":130},{"partyNum":17,"totalVotes":797,"machineVotes":0,"paperVotes":797},{"partyNum":18,"totalVotes":2,"machineVotes":0,"paperVotes":2},{"partyNum":21,"totalVotes":313,"machineVotes":0,"paperVotes":313},{"partyNum":12,"totalVotes":12,"machineVotes":0,"paperVotes":12},{"partyNum":19,"totalVotes":6,"machineVotes":0,"paperVotes":6},{"partyNum":20,"totalVotes":14,"machineVotes":0,"paperVotes":14},{"partyNum":22,"totalVotes":12,"machineVotes":0,"paperVotes":12},{"partyNum":1,"totalVotes":6,"machineVotes":0,"paperVotes":6}],"protocol":{"ballotsReceived":20900,"numAdditionalVoters":54,"numInvalidAndDestroyedPaperBallots":29,"numInvalidBallotsFound":610,"numPaperBallotsFound":10709,"numRegisteredVoters":19853,"numUnusedPaperBallots":10153,"numValidNoOnePaperVotes":229,"numValidVotes":10709,"totalActualVoters":11548}}},{"key":"BG413","ekatte":"20585","name":"Делчево","oblast":"BLG","obshtina":"BLG11","kmetstvo":"BLG11-00","t_v_m":"с.","sections":[],"results":{"votes":[{"partyNum":3,"totalVotes":1,"machineVotes":0,"paperVotes":1},{"partyNum":4,"totalVotes":1,"machineVotes":0,"paperVotes":1},{"partyNum":9,"totalVotes":1,"machineVotes":0,"paperVotes":1},{"partyNum":10,"totalVotes":14,"machineVotes":0,"paperVotes":14},{"partyNum":11,"totalVotes":13,"machineVotes":0,"paperVotes":13},{"partyNum":17,"totalVotes":3,"machineVotes":0,"paperVotes":3}],"protocol":{"ballotsReceived":100,"numAdditionalVoters":8,"numInvalidAndDestroyedPaperBallots":1,"numInvalidBallotsFound":8,"numPaperBallotsFound":41,"numRegisteredVoters":44,"numUnusedPaperBallots":58,"numValidVotes":41,"totalActualVoters":49}}},{"key":"BG413","ekatte":"21680","name":"Добротино","oblast":"BLG","obshtina":"BLG11","kmetstvo":"BLG11-00","t_v_m":"с.","sections":[],"results":{"votes":[{"partyNum":8,"totalVotes":1,"machineVotes":0,"paperVotes":1},{"partyNum":10,"totalVotes":14,"machineVotes":0,"paperVotes":14},{"partyNum":11,"totalVotes":3,"machineVotes":0,"paperVotes":3},{"partyNum":17,"totalVotes":3,"machineVotes":0,"paperVotes":3},{"partyNum":21,"totalVotes":1,"machineVotes":0,"paperVotes":1}],"protocol":{"ballotsReceived":100,"numAdditionalVoters":8,"numInvalidAndDestroyedPaperBallots":1,"numInvalidBallotsFound":5,"numPaperBallotsFound":27,"numRegisteredVoters":30,"numUnusedPaperBallots":72,"numValidVotes":27,"totalActualVoters":32}}},{"key":"BG413","ekatte":"38666","name":"Корница","oblast":"BLG","obshtina":"BLG11","kmetstvo":"BLG11-07","t_v_m":"с.","sections":[],"results":{"votes":[{"partyNum":6,"totalVotes":10,"machineVotes":0,"paperVotes":10},{"partyNum":7,"totalVotes":3,"machineVotes":0,"paperVotes":3},{"partyNum":9,"totalVotes":429,"machineVotes":0,"paperVotes":429},{"partyNum":10,"totalVotes":36,"machineVotes":0,"paperVotes":36},{"partyNum":11,"totalVotes":35,"machineVotes":0,"paperVotes":35},{"partyNum":12,"totalVotes":1,"machineVotes":0,"paperVotes":1},{"partyNum":13,"totalVotes":275,"machineVotes":0,"paperVotes":275},{"partyNum":16,"totalVotes":3,"machineVotes":0,"paperVotes":3},{"partyNum":17,"totalVotes":10,"machineVotes":0,"paperVotes":10},{"partyNum":19,"totalVotes":1,"machineVotes":0,"paperVotes":1},{"partyNum":21,"totalVotes":3,"machineVotes":0,"paperVotes":3},{"partyNum":4,"totalVotes":3,"machineVotes":0,"paperVotes":3},{"partyNum":14,"totalVotes":1,"machineVotes":0,"paperVotes":1}],"protocol":{"ballotsReceived":1900,"numAdditionalVoters":20,"numInvalidAndDestroyedPaperBallots":3,"numInvalidBallotsFound":78,"numPaperBallotsFound":898,"numRegisteredVoters":1780,"numUnusedPaperBallots":999,"numValidNoOnePaperVotes":10,"numValidVotes":898,"totalActualVoters":986}}},{"key":"BG413","ekatte":"44416","name":"Лъжница","oblast":"BLG","obshtina":"BLG11","kmetstvo":"BLG11-08","t_v_m":"с.","sections":[],"results":{"votes":[{"partyNum":4,"totalVotes":6,"machineVotes":0,"paperVotes":6},{"partyNum":6,"totalVotes":1,"machineVotes":0,"paperVotes":1},{"partyNum":9,"totalVotes":458,"machineVotes":0,"paperVotes":458},{"partyNum":10,"totalVotes":25,"machineVotes":0,"paperVotes":25},{"partyNum":11,"totalVotes":20,"machineVotes":0,"paperVotes":20},{"partyNum":12,"totalVotes":1,"machineVotes":0,"paperVotes":1},{"partyNum":13,"totalVotes":401,"machineVotes":0,"paperVotes":401},{"partyNum":21,"totalVotes":2,"machineVotes":0,"paperVotes":2},{"partyNum":2,"totalVotes":1,"machineVotes":0,"paperVotes":1},{"partyNum":8,"totalVotes":1,"machineVotes":0,"paperVotes":1}],"protocol":{"ballotsReceived":1700,"numAdditionalVoters":29,"numInvalidAndDestroyedPaperBallots":3,"numInvalidBallotsFound":126,"numPaperBallotsFound":1044,"numRegisteredVoters":1488,"numUnusedPaperBallots":653,"numValidNoOnePaperVotes":2,"numValidVotes":1044,"totalActualVoters":1172}}},{"key":"BG413","ekatte":"49432","name":"Мосомище","oblast":"BLG","obshtina":"BLG11","kmetstvo":"BLG11-09","t_v_m":"с.","sections":[],"results":{"votes":[]}},{"key":"BG413","ekatte":"87802","name":"Попови ливади","oblast":"BLG","obshtina":"BLG11","kmetstvo":"BLG11-00","t_v_m":"с.","sections":[],"results":{"votes":[]}}]