[{"ekatte":"14550","partyNum":17,"totalVotes":1,"pref":"104","oblast":"HKV","obshtina":"HKV34","allVotes":250,"partyVotes":2,"partyPrefs":1},{"ekatte":"21052","partyNum":17,"totalVotes":4,"pref":"104","oblast":"HKV","obshtina":"HKV09","allVotes":11045,"partyVotes":157,"partyPrefs":52},{"ekatte":"21539","partyNum":17,"totalVotes":1,"pref":"104","oblast":"HKV","obshtina":"HKV09","allVotes":331,"partyVotes":3,"partyPrefs":1},{"ekatte":"44570","partyNum":17,"totalVotes":1,"pref":"104","oblast":"HKV","obshtina":"HKV17","allVotes":2442,"partyVotes":16,"partyPrefs":6},{"ekatte":"72761","partyNum":17,"totalVotes":1,"pref":"104","oblast":"HKV","obshtina":"HKV32","allVotes":1567,"partyVotes":12,"partyPrefs":3},{"ekatte":"77195","partyNum":17,"totalVotes":1,"pref":"104","oblast":"HKV","obshtina":"HKV34","allVotes":24482,"partyVotes":147,"partyPrefs":40},{"ekatte":"04128","partyNum":17,"totalVotes":1,"pref":"104","oblast":"HKV","obshtina":"HKV33","allVotes":319,"partyVotes":1,"partyPrefs":1}]