[{"ekatte":"15944","partyNum":21,"totalVotes":1,"pref":"109","oblast":"SLV","obshtina":"SLV24","allVotes":1173,"partyVotes":17,"partyPrefs":9},{"ekatte":"29194","partyNum":21,"totalVotes":1,"pref":"109","oblast":"SLV","obshtina":"SLV20","allVotes":972,"partyVotes":70,"partyPrefs":28},{"ekatte":"48725","partyNum":21,"totalVotes":1,"pref":"109","oblast":"SLV","obshtina":"SLV16","allVotes":331,"partyVotes":11,"partyPrefs":6},{"ekatte":"67338","partyNum":21,"totalVotes":15,"pref":"109","oblast":"SLV","obshtina":"SLV20","allVotes":38390,"partyVotes":1129,"partyPrefs":582},{"ekatte":"72165","partyNum":21,"totalVotes":1,"pref":"109","oblast":"SLV","obshtina":"SLV24","allVotes":2053,"partyVotes":58,"partyPrefs":29}]