{"stats":[{"elections_date":"2017_03_26","party":{"number":6,"name":"ВОЛЯ","color":"rgb(0, 115, 143)","nickName":"ВОЛЯ"},"preferences":[{"oblast":"GAB","pref":"105","preferences":60},{"oblast":"SLS","pref":"104","preferences":49}]},{"elections_date":"2014_10_05","preferences":[]},{"elections_date":"2013_05_12","preferences":[]},{"elections_date":"2009_07_05","preferences":[]},{"elections_date":"2005_06_25","preferences":[]}],"top_sections":[{"section":"203100118","partyNum":6,"pref":"104","totalVotes":5,"oblast":"SLS","obshtina":"SLS31","ekatte":"66425","partyVotes":35,"allVotes":427,"partyPrefs":8},{"section":"072900011","partyNum":6,"pref":"105","totalVotes":4,"oblast":"GAB","obshtina":"GAB29","ekatte":"65927","partyVotes":35,"allVotes":474,"partyPrefs":6},{"section":"070500011","partyNum":6,"pref":"105","totalVotes":3,"oblast":"GAB","obshtina":"GAB05","ekatte":"14218","partyVotes":28,"allVotes":266,"partyPrefs":3},{"section":"070500043","partyNum":6,"pref":"105","totalVotes":3,"oblast":"GAB","obshtina":"GAB05","ekatte":"14218","partyVotes":22,"allVotes":347,"partyPrefs":9},{"section":"073500006","partyNum":6,"pref":"105","totalVotes":3,"oblast":"GAB","obshtina":"GAB35","ekatte":"73403","partyVotes":37,"allVotes":348,"partyPrefs":8},{"section":"203400706","partyNum":6,"pref":"104","totalVotes":3,"oblast":"SLS","obshtina":"SLS34","ekatte":"73496","partyVotes":24,"allVotes":483,"partyPrefs":8},{"section":"070500001","partyNum":6,"pref":"105","totalVotes":2,"oblast":"GAB","obshtina":"GAB05","ekatte":"14218","partyVotes":81,"allVotes":512,"partyPrefs":6},{"section":"070500006","partyNum":6,"pref":"105","totalVotes":2,"oblast":"GAB","obshtina":"GAB05","ekatte":"14218","partyVotes":27,"allVotes":359,"partyPrefs":3},{"section":"070500075","partyNum":6,"pref":"105","totalVotes":2,"oblast":"GAB","obshtina":"GAB05","ekatte":"14218","partyVotes":39,"allVotes":422,"partyPrefs":8},{"section":"071200001","partyNum":6,"pref":"105","totalVotes":2,"oblast":"GAB","obshtina":"GAB12","ekatte":"23947","partyVotes":21,"allVotes":220,"partyPrefs":4}],"top_settlements":[{"ekatte":"14218","partyNum":6,"totalVotes":27,"pref":"105","oblast":"GAB","obshtina":"GAB05","allVotes":27909,"partyVotes":1960,"partyPrefs":277},{"ekatte":"66425","partyNum":6,"totalVotes":24,"pref":"104","oblast":"SLS","obshtina":"SLS31","allVotes":17754,"partyVotes":1036,"partyPrefs":203},{"ekatte":"65927","partyNum":6,"totalVotes":13,"pref":"105","oblast":"GAB","obshtina":"GAB29","allVotes":10566,"partyVotes":782,"partyPrefs":99},{"ekatte":"23947","partyNum":6,"totalVotes":7,"pref":"105","oblast":"GAB","obshtina":"GAB12","allVotes":3512,"partyVotes":283,"partyPrefs":58},{"ekatte":"73496","partyNum":6,"totalVotes":7,"pref":"104","oblast":"SLS","obshtina":"SLS34","allVotes":4266,"partyVotes":140,"partyPrefs":22},{"ekatte":"73403","partyNum":6,"totalVotes":6,"pref":"105","oblast":"GAB","obshtina":"GAB35","allVotes":4535,"partyVotes":423,"partyPrefs":62},{"ekatte":"00895","partyNum":6,"totalVotes":5,"pref":"104","oblast":"SLS","obshtina":"SLS31","allVotes":2922,"partyVotes":194,"partyPrefs":38},{"ekatte":"24030","partyNum":6,"totalVotes":3,"pref":"104","oblast":"SLS","obshtina":"SLS10","allVotes":3100,"partyVotes":99,"partyPrefs":25},{"ekatte":"41143","partyNum":6,"totalVotes":2,"pref":"104","oblast":"SLS","obshtina":"SLS31","allVotes":1840,"partyVotes":62,"partyPrefs":15},{"ekatte":"58253","partyNum":6,"totalVotes":2,"pref":"104","oblast":"SLS","obshtina":"SLS34","allVotes":304,"partyVotes":8,"partyPrefs":4}]}